package marg.asm


object Opcodes {
  // opcodes // visit method (- = idem)

  val NOP = 0 // visitInsn
  val ACONST_NULL = 1 // -
  val ICONST_M1 = 2 // -
  val ICONST_0 = 3 // -
  val ICONST_1 = 4 // -
  val ICONST_2 = 5 // -
  val ICONST_3 = 6 // -
  val ICONST_4 = 7 // -
  val ICONST_5 = 8 // -
  val LCONST_0 = 9 // -
  val LCONST_1 = 10 // -
  val FCONST_0 = 11 // -
  val FCONST_1 = 12 // -
  val FCONST_2 = 13 // -
  val DCONST_0 = 14 // -
  val DCONST_1 = 15 // -
  val BIPUSH = 16 // visitIntInsn
  val SIPUSH = 17 // -
  val LDC = 18 // visitLdcInsn
  // val LDC_W = 19 // -
  // val LDC2_W = 20 // -
  val ILOAD = 21 // visitVarInsn
  val LLOAD = 22 // -
  val FLOAD = 23 // -
  val DLOAD = 24 // -
  val ALOAD = 25 // -
  // val ILOAD_0 = 26 // -
  // val ILOAD_1 = 27 // -
  // val ILOAD_2 = 28 // -
  // val ILOAD_3 = 29 // -
  // val LLOAD_0 = 30 // -
  // val LLOAD_1 = 31 // -
  // val LLOAD_2 = 32 // -
  // val LLOAD_3 = 33 // -
  // val FLOAD_0 = 34 // -
  // val FLOAD_1 = 35 // -
  // val FLOAD_2 = 36 // -
  // val FLOAD_3 = 37 // -
  // val DLOAD_0 = 38 // -
  // val DLOAD_1 = 39 // -
  // val DLOAD_2 = 40 // -
  // val DLOAD_3 = 41 // -
  // val ALOAD_0 = 42 // -
  // val ALOAD_1 = 43 // -
  // val ALOAD_2 = 44 // -
  // val ALOAD_3 = 45 // -
  val IALOAD = 46 // visitInsn
  val LALOAD = 47 // -
  val FALOAD = 48 // -
  val DALOAD = 49 // -
  val AALOAD = 50 // -
  val BALOAD = 51 // -
  val CALOAD = 52 // -
  val SALOAD = 53 // -
  val ISTORE = 54 // visitVarInsn
  val LSTORE = 55 // -
  val FSTORE = 56 // -
  val DSTORE = 57 // -
  val ASTORE = 58 // -
  // val ISTORE_0 = 59 // -
  // val ISTORE_1 = 60 // -
  // val ISTORE_2 = 61 // -
  // val ISTORE_3 = 62 // -
  // val LSTORE_0 = 63 // -
  // val LSTORE_1 = 64 // -
  // val LSTORE_2 = 65 // -
  // val LSTORE_3 = 66 // -
  // val FSTORE_0 = 67 // -
  // val FSTORE_1 = 68 // -
  // val FSTORE_2 = 69 // -
  // val FSTORE_3 = 70 // -
  // val DSTORE_0 = 71 // -
  // val DSTORE_1 = 72 // -
  // val DSTORE_2 = 73 // -
  // val DSTORE_3 = 74 // -
  // val ASTORE_0 = 75 // -
  // val ASTORE_1 = 76 // -
  // val ASTORE_2 = 77 // -
  // val ASTORE_3 = 78 // -
  val IASTORE = 79 // visitInsn
  val LASTORE = 80 // -
  val FASTORE = 81 // -
  val DASTORE = 82 // -
  val AASTORE = 83 // -
  val BASTORE = 84 // -
  val CASTORE = 85 // -
  val SASTORE = 86 // -
  val POP = 87 // -
  val POP2 = 88 // -
  val DUP = 89 // -
  val DUP_X1 = 90 // -
  val DUP_X2 = 91 // -
  val DUP2 = 92 // -
  val DUP2_X1 = 93 // -
  val DUP2_X2 = 94 // -
  val SWAP = 95 // -
  val IADD = 96 // -
  val LADD = 97 // -
  val FADD = 98 // -
  val DADD = 99 // -
  val ISUB = 100 // -
  val LSUB = 101 // -
  val FSUB = 102 // -
  val DSUB = 103 // -
  val IMUL = 104 // -
  val LMUL = 105 // -
  val FMUL = 106 // -
  val DMUL = 107 // -
  val IDIV = 108 // -
  val LDIV = 109 // -
  val FDIV = 110 // -
  val DDIV = 111 // -
  val IREM = 112 // -
  val LREM = 113 // -
  val FREM = 114 // -
  val DREM = 115 // -
  val INEG = 116 // -
  val LNEG = 117 // -
  val FNEG = 118 // -
  val DNEG = 119 // -
  val ISHL = 120 // -
  val LSHL = 121 // -
  val ISHR = 122 // -
  val LSHR = 123 // -
  val IUSHR = 124 // -
  val LUSHR = 125 // -
  val IAND = 126 // -
  val LAND = 127 // -
  val IOR = 128 // -
  val LOR = 129 // -
  val IXOR = 130 // -
  val LXOR = 131 // -
  val IINC = 132 // visitIincInsn
  val I2L = 133 // visitInsn
  val I2F = 134 // -
  val I2D = 135 // -
  val L2I = 136 // -
  val L2F = 137 // -
  val L2D = 138 // -
  val F2I = 139 // -
  val F2L = 140 // -
  val F2D = 141 // -
  val D2I = 142 // -
  val D2L = 143 // -
  val D2F = 144 // -
  val I2B = 145 // -
  val I2C = 146 // -
  val I2S = 147 // -
  val LCMP = 148 // -
  val FCMPL = 149 // -
  val FCMPG = 150 // -
  val DCMPL = 151 // -
  val DCMPG = 152 // -
  val IFEQ = 153 // visitJumpInsn
  val IFNE = 154 // -
  val IFLT = 155 // -
  val IFGE = 156 // -
  val IFGT = 157 // -
  val IFLE = 158 // -
  val IF_ICMPEQ = 159 // -
  val IF_ICMPNE = 160 // -
  val IF_ICMPLT = 161 // -
  val IF_ICMPGE = 162 // -
  val IF_ICMPGT = 163 // -
  val IF_ICMPLE = 164 // -
  val IF_ACMPEQ = 165 // -
  val IF_ACMPNE = 166 // -
  val GOTO = 167 // -
  val JSR = 168 // -
  val RET = 169 // visitVarInsn
  val TABLESWITCH = 170 // visiTableSwitchInsn
  val LOOKUPSWITCH = 171 // visitLookupSwitch
  val IRETURN = 172 // visitInsn
  val LRETURN = 173 // -
  val FRETURN = 174 // -
  val DRETURN = 175 // -
  val ARETURN = 176 // -
  val RETURN = 177 // -
  val GETSTATIC = 178 // visitFieldInsn
  val PUTSTATIC = 179 // -
  val GETFIELD = 180 // -
  val PUTFIELD = 181 // -
  val INVOKEVIRTUAL = 182 // visitMethodInsn
  val INVOKESPECIAL = 183 // -
  val INVOKESTATIC = 184 // -
  val INVOKEINTERFACE = 185 // -
  val INVOKEDYNAMIC = 186 // visitInvokeDynamicInsn
  val NEW = 187 // visitTypeInsn
  val NEWARRAY = 188 // visitIntInsn
  val ANEWARRAY = 189 // visitTypeInsn
  val ARRAYLENGTH = 190 // visitInsn
  val ATHROW = 191 // -
  val CHECKCAST = 192 // visitTypeInsn
  val INSTANCEOF = 193 // -
  val MONITORENTER = 194 // visitInsn
  val MONITOREXIT = 195 // -
  // val WIDE = 196 // NOT VISITED
  val MULTIANEWARRAY = 197 // visitMultiANewArrayInsn
  val IFNULL = 198 // visitJumpInsn
  val IFNONNULL = 199 // -
  // val GOTO_W = 200 // -
  // val JSR_W = 201 // -
}
